{
  "Missouri River": ["Stipek", "Diamond Willow", "Sidney Bridge"],
  "Madison River": ["Raynolds' Pass", "Three Dollar Bridge", "Lyons Bridge", "McAtee Bridge", "Varney Bridge", 
  "Eight Mile Ford", "Burnt Tree Hole", "Ennis", "Valley Garden", "Damselfly",
   "Black's Ford", "Greycliff","Cobblestone","Milwaukee","Blackbird"],
  "Clarks Fork Yellowstone River": ["Clarks Fork Yellowstone", "Bundy Bridge"],
  "Yellowstone River": ["Queen of the Waters", "Brogan's Landing", "Slip & Slide", "Crystal Cross",
   "Point of Rocks", "Emigrant", "Emigrant West", "Grey Owl", "Chicory", "Dan Bailey", "Loch Leven", "Mallard's Rest",
  "Pine Creek", "Carter's Bridge", "Jim Posewitz Free River", "Mayor's Landing", "Highway 89 Bridge", "Sheep Mountain","Springdale Bridge", "Grey Bear", "Otter Creek"],
  "Gallatin River": ["Kirk Wildlife Refuge", "Axtell Bridge", "Shed's Bridge", "Cameron Bridge", "Erwin Bridge", "Four Corners", "Gallatin Forks", "Bud Lilly"],
  "Jefferson River": ["Drouillard","Williams' Bridge","Sappington Bridge","Limespur","Mayflower Bridge",
  "Kountz Bridge","Parrot Castle","Silver Star","","","","","",""]

}
